tmux_pwd_fzf/__init__.py
tmux_pwd_fzf/main.py
tmux_pwd_fzf-1.0.0.dist-info/METADATA
tmux_pwd_fzf-1.0.0.dist-info/WHEEL
tmux_pwd_fzf-1.0.0.dist-info/entry_points.txt
tmux_pwd_fzf-1.0.0.dist-info/RECORD
