Metadata-Version: 2.4
Name: tmux-pwd-fzf
Version: 1.0.0
Summary: Select a tmux window based on its name and the directory it is in
License-Expression: MIT
Keywords: fzf,pane,selector,terminal,tmux
Classifier: Development Status :: 3 - Alpha
Classifier: Environment :: Console
Classifier: Intended Audience :: Developers
Classifier: License :: OSI Approved :: MIT License
Classifier: Operating System :: MacOS
Classifier: Operating System :: POSIX :: Linux
Classifier: Programming Language :: Python :: 3
Requires-Python: >=3.10
